agc/__init__.py
agc/model.py
audiogen_agc-0.1.1.dist-info/LICENSE
audiogen_agc-0.1.1.dist-info/LICENSE_dac
audiogen_agc-0.1.1.dist-info/METADATA
audiogen_agc-0.1.1.dist-info/WHEEL
audiogen_agc-0.1.1.dist-info/top_level.txt
audiogen_agc-0.1.1.dist-info/RECORD
