Metadata-Version: 2.1
Name: audiogen-agc
Version: 0.1.1
Summary: Audiogen Codec
Home-page: https://github.com/AudiogenAI/agc
Author: Elio Pascarelli
Author-email: elio@audiogen.co
Classifier: Programming Language :: Python :: 3.10
Classifier: License :: Other/Proprietary License
Classifier: Operating System :: POSIX :: Linux
Requires-Python: >=3.9
License-File: LICENSE
License-File: LICENSE_dac
Requires-Dist: torch
Requires-Dist: torchaudio
Requires-Dist: transformers
Requires-Dist: einops
Requires-Dist: numpy
